README.md
setup.cfg
setup.py
daigle_dist/Binomialdistribution.py
daigle_dist/Gaussiandistribution.py
daigle_dist/Generaldistribution.py
daigle_dist/__init__.py
daigle_dist.egg-info/PKG-INFO
daigle_dist.egg-info/SOURCES.txt
daigle_dist.egg-info/dependency_links.txt
daigle_dist.egg-info/not-zip-safe
daigle_dist.egg-info/top_level.txt