Metadata-Version: 2.1
Name: daigle-dist
Version: 0.1.3.1
Summary: Gaussian and Binomial Distributions
Home-page: https://github.com/ChristopherDaigle/daigle_dist.git
Author: Christopher Daigle
Author-email: pcjdaigle@gmail.com
License: UNKNOWN
Platform: UNKNOWN
Classifier: Programming Language :: Python :: 3
Classifier: License :: OSI Approved :: MIT License
Classifier: Operating System :: OS Independent
Requires-Python: >=3.6
